MANIFEST.in
README.rst
requirements.txt
setup.cfg
setup.py
django_vehicles_maintenance/iniciarservidor.cmd
django_vehicles_maintenance/manage.py
django_vehicles_maintenance/manage.pyc
django_vehicles_maintenance.egg-info/PKG-INFO
django_vehicles_maintenance.egg-info/SOURCES.txt
django_vehicles_maintenance.egg-info/dependency_links.txt
django_vehicles_maintenance.egg-info/requires.txt
django_vehicles_maintenance.egg-info/top_level.txt
django_vehicles_maintenance/maintenance/__init__.py
django_vehicles_maintenance/maintenance/__init__.pyc
django_vehicles_maintenance/maintenance/settings.py
django_vehicles_maintenance/maintenance/settings.pyc
django_vehicles_maintenance/maintenance/urls.py
django_vehicles_maintenance/maintenance/urls.pyc
django_vehicles_maintenance/maintenance/wsgi.py
django_vehicles_maintenance/maintenance/wsgi.pyc
django_vehicles_maintenance/maintenance/main/__init__.py
django_vehicles_maintenance/maintenance/main/__init__.pyc
django_vehicles_maintenance/maintenance/main/admin.py
django_vehicles_maintenance/maintenance/main/admin.pyc
django_vehicles_maintenance/maintenance/main/forms.py
django_vehicles_maintenance/maintenance/main/forms.pyc
django_vehicles_maintenance/maintenance/main/models.py
django_vehicles_maintenance/maintenance/main/models.pyc
django_vehicles_maintenance/maintenance/main/tests.py
django_vehicles_maintenance/maintenance/main/tests.pyc
django_vehicles_maintenance/maintenance/main/urls.py
django_vehicles_maintenance/maintenance/main/urls.pyc
django_vehicles_maintenance/maintenance/main/views.py
django_vehicles_maintenance/maintenance/main/views.py.pdf
django_vehicles_maintenance/maintenance/main/views.pyc
django_vehicles_maintenance/maintenance/main/migrations/0001_initial.pyc
django_vehicles_maintenance/maintenance/main/migrations/0002_auto__chg_field_storage_tank_maintenance_storage_tank__chg_field_radio.pyc
django_vehicles_maintenance/maintenance/main/migrations/0003_auto__add_field_storage_tank_overfill_valve__add_field_storage_tank_te.pyc
django_vehicles_maintenance/maintenance/main/migrations/0004_auto__add_field_carburetion_tank_service_valve__add_field_carburetion_.pyc
