Metadata-Version: 1.0
Name: django-vehicles-maintenance
Version: 0.0.6
Summary: `mantenimiento de vehiculos
Home-page: UNKNOWN
Author: jesus Manuel Herrera
Author-email: jesusmahererra@gmail.com
License: BSD License
Platform: UNKNOWN
Classifier: Environment :: Web Environment
Classifier: Framework :: Django
Classifier: Intended Audience :: Developers
Classifier: License :: OSI Approved :: BSD License
Classifier: Operating System :: OS Independent
Classifier: Programming Language :: Python
Classifier: Programming Language :: Python :: 2.6
Classifier: Programming Language :: Python :: 2.7
Classifier: Topic :: Internet :: WWW/HTTP
Classifier: Topic :: Internet :: WWW/HTTP :: Dynamic Content
